pennylane_rigetti/__init__.py
pennylane_rigetti/_version.py
pennylane_rigetti/converter.py
pennylane_rigetti/device.py
pennylane_rigetti/numpy_wavefunction.py
pennylane_rigetti/ops.py
pennylane_rigetti/qc.py
pennylane_rigetti/qpu.py
pennylane_rigetti/qvm.py
pennylane_rigetti/wavefunction.py
PennyLane_Rigetti-0.39.0.dist-info/LICENSE
PennyLane_Rigetti-0.39.0.dist-info/METADATA
PennyLane_Rigetti-0.39.0.dist-info/WHEEL
PennyLane_Rigetti-0.39.0.dist-info/entry_points.txt
PennyLane_Rigetti-0.39.0.dist-info/top_level.txt
PennyLane_Rigetti-0.39.0.dist-info/RECORD
