Metadata-Version: 2.1
Name: PennyLane-Rigetti
Version: 0.39.0
Summary: Rigetti backend for the PennyLane library
Home-page: https://github.com/PennyLaneAI/pennylane-rigetti
Maintainer: Xanadu Inc.
Maintainer-email: software@xanadu.ai
License: BSD 3-Clause
Classifier: Development Status :: 4 - Beta
Classifier: Environment :: Console
Classifier: Intended Audience :: Science/Research
Classifier: License :: OSI Approved :: BSD License
Classifier: Natural Language :: English
Classifier: Operating System :: POSIX
Classifier: Operating System :: MacOS :: MacOS X
Classifier: Operating System :: POSIX :: Linux
Classifier: Operating System :: Microsoft :: Windows
Classifier: Programming Language :: Python
Classifier: Programming Language :: Python :: 3
Classifier: Programming Language :: Python :: 3.10
Classifier: Programming Language :: Python :: 3.11
Classifier: Programming Language :: Python :: 3.12
Classifier: Programming Language :: Python :: 3 :: Only
Classifier: Topic :: Scientific/Engineering :: Physics
Provides: pennylane_rigetti
License-File: LICENSE
Requires-Dist: numpy>=1.21
Requires-Dist: networkx<3.0,>=2.5
Requires-Dist: pennylane>=0.38
Requires-Dist: pyquil<4.0.0,>=3.0.0
Requires-Dist: qcs-api-client<0.22.0,>=0.20.13
Provides-Extra: test
Requires-Dist: flaky>=3.7.0; extra == "test"
Requires-Dist: pytest>=7.2.1; extra == "test"
Requires-Dist: pytest-cov>=4.0.0; extra == "test"
Requires-Dist: pytest-mock>=3.10.0; extra == "test"
Requires-Dist: pytest-benchmark; extra == "test"
Requires-Dist: wheel>=0.38.4; extra == "test"
